{
  "$schema": "./node_modules/@angular/cli/lib/config/schema.json",
  "project": {
    "name": "alpha-it"
  },
  "apps": [
    {
      "root": "src",
      "outDir": "dist",
      "assets": [
        "assets",
        "favicon.ico"
      ],
      "index": "index.html",
      "main": "main.ts",
      "polyfills": "polyfills.ts",
      "test": "test.ts",
      "tsconfig": "tsconfig.app.json",
      "testTsconfig": "tsconfig.spec.json",
      "prefix": "app",
      "styles": [
        "styles.css",
        "assets/resources/css/style.css",
        "assets/resources/css/transitions.css",
        "assets/resources/css/queries-style.css"
      ],
      "scripts": [
        "assets/vendors/js/Projector.js",
        "assets/vendors/js/CanvasRenderer.js",
        "assets/vendors/js/stats.min.js",
        "assets/vendors/js/bgthreed.js",
        "assets/resources/js/script.js",
        "assets/resources/js/step-by-step-boxes.js"
      ],
      "environmentSource": "environments/environment.ts",
      "environments": {
        "dev": "environments/environment.ts",
        "prod": "environments/environment.prod.ts"
      }
    }
  ],
  "e2e": {
    "protractor": {
      "config": "./protractor.conf.js"
    }
  },
  "lint": [
    {
      "project": "src/tsconfig.app.json",
      "exclude": "**/node_modules/**"
    },
    {
      "project": "src/tsconfig.spec.json",
      "exclude": "**/node_modules/**"
    },
    {
      "project": "e2e/tsconfig.e2e.json",
      "exclude": "**/node_modules/**"
    }
  ],
  "test": {
    "karma": {
      "config": "./karma.conf.js"
    }
  },
  "defaults": {
    "styleExt": "css",
    "component": {}
  }
}
